README.md
nothoney.py
setup.py
nothoney.egg-info/PKG-INFO
nothoney.egg-info/SOURCES.txt
nothoney.egg-info/dependency_links.txt
nothoney.egg-info/top_level.txt