Metadata-Version: 2.1
Name: nothoney
Version: 0.1.2
Summary: recursively iterate through a nested (n-deep) dictionary or JSON object/file
Home-page: https://github.com/vesche/nothoney
Author: Austin Jackson
Author-email: vesche@protonmail.com
License: MIT
Classifier: Development Status :: 5 - Production/Stable
Classifier: License :: Public Domain
Classifier: Programming Language :: Python :: 3
Classifier: Programming Language :: Python :: 3.10
